certum_client/__init__.py
certum_client/client.py
certum_client/py.typed
certum_client-0.1.0.dist-info/licenses/LICENSE
certum_client-0.1.0.dist-info/METADATA
certum_client-0.1.0.dist-info/WHEEL
certum_client-0.1.0.dist-info/top_level.txt
certum_client-0.1.0.dist-info/RECORD
