Metadata-Version: 2.4
Name: certum-client
Version: 0.1.0
Summary: Python client (sync + async) for the CertumTree API.
Author-email: Mike Issakov <nye.ivangay@example.com>
Project-URL: Repository, https://github.com/hex358/certum_client
Keywords: certum,certumtree,client,http,async,httpx
Classifier: Development Status :: 3 - Alpha
Classifier: Intended Audience :: Developers
Classifier: License :: OSI Approved :: MIT License
Classifier: Programming Language :: Python
Classifier: Programming Language :: Python :: 3
Classifier: Programming Language :: Python :: 3 :: Only
Classifier: Programming Language :: Python :: 3.8
Classifier: Programming Language :: Python :: 3.9
Classifier: Programming Language :: Python :: 3.10
Classifier: Programming Language :: Python :: 3.11
Classifier: Programming Language :: Python :: 3.12
Classifier: Typing :: Typed
Requires-Python: >=3.8
License-File: LICENSE
Requires-Dist: httpx>=0.27.0
Dynamic: license-file
